patek/__init__.py
patek/exceptions.py
patek/functions.py
patek/io.py
patek-0.5.1.dist-info/LICENSE
patek-0.5.1.dist-info/METADATA
patek-0.5.1.dist-info/WHEEL
patek-0.5.1.dist-info/top_level.txt
patek-0.5.1.dist-info/RECORD
